youdaoai-0.2.3.dist-info/METADATA
youdaoai-0.2.3.dist-info/WHEEL
youdaoai-0.2.3.dist-info/entry_points.txt
youdaoai-0.2.3.dist-info/licenses/LICENSE
youdaoai/__init__.py
youdaoai/_utils.py
youdaoai/client.py
youdaoai/types.py
youdaoai-0.2.3.dist-info/RECORD
