Metadata-Version: 2.1
Name: youdaoai
Version: 0.2.3
Summary: Python SDK for Youdao AI.
Author-Email: Anderson <andersonby@163.com>
License: MIT
Project-URL: Homepage, https://github.com/AndersonBY/python-youdao-ai
Requires-Python: >=3.9
Requires-Dist: httpx>=0.28.1
Requires-Dist: pydantic>=2.10.3
